{
  "$schema": "https://developer.microsoft.com/json-schemas/fabric/item/report/definition/visualContainer/2.10.0/schema.json",
  "name": "890108d3eb725e8e4bd8",
  "position": {
    "x": 614.43596236668452,
    "y": 173.89697048113715,
    "z": 14000,
    "height": 220.26949594277372,
    "width": 309.70222361878712,
    "tabOrder": 14000
  },
  "visual": {
    "visualType": "donutChart",
    "query": {
      "queryState": {
        "Category": {
          "projections": [
            {
              "field": {
                "Column": {
                  "Expression": {
                    "SourceRef": {
                      "Entity": "Customer Lookup"
                    }
                  },
                  "Property": "MaritalStatus"
                }
              },
              "queryRef": "Customer Lookup.MaritalStatus",
              "nativeQueryRef": "MaritalStatus",
              "active": true
            }
          ]
        },
        "Y": {
          "projections": [
            {
              "field": {
                "Measure": {
                  "Expression": {
                    "SourceRef": {
                      "Entity": "Fact_Sales"
                    }
                  },
                  "Property": "Total Orders"
                }
              },
              "queryRef": "Fact_Sales.Total Orders",
              "nativeQueryRef": "Total Orders"
            }
          ]
        }
      },
      "sortDefinition": {
        "sort": [
          {
            "field": {
              "Measure": {
                "Expression": {
                  "SourceRef": {
                    "Entity": "Fact_Sales"
                  }
                },
                "Property": "Total Orders"
              }
            },
            "direction": "Descending"
          }
        ],
        "isDefaultSort": true
      }
    },
    "visualContainerObjects": {
      "title": [
        {
          "properties": {
            "fontColor": {
              "solid": {
                "color": {
                  "expr": {
                    "ThemeDataColor": {
                      "ColorId": 2,
                      "Percent": -0.25
                    }
                  }
                }
              }
            },
            "fontSize": {
              "expr": {
                "Literal": {
                  "Value": "16D"
                }
              }
            }
          }
        }
      ],
      "border": [
        {
          "properties": {
            "show": {
              "expr": {
                "Literal": {
                  "Value": "true"
                }
              }
            },
            "color": {
              "solid": {
                "color": {
                  "expr": {
                    "ThemeDataColor": {
                      "ColorId": 2,
                      "Percent": 0.4
                    }
                  }
                }
              }
            },
            "width": {
              "expr": {
                "Literal": {
                  "Value": "2D"
                }
              }
            },
            "radius": {
              "expr": {
                "Literal": {
                  "Value": "12D"
                }
              }
            }
          }
        }
      ],
      "dropShadow": [
        {
          "properties": {
            "show": {
              "expr": {
                "Literal": {
                  "Value": "true"
                }
              }
            },
            "color": {
              "solid": {
                "color": {
                  "expr": {
                    "ThemeDataColor": {
                      "ColorId": 2,
                      "Percent": 0.4
                    }
                  }
                }
              }
            }
          }
        }
      ]
    },
    "drillFilterOtherVisuals": true
  }
}